{
	"class" : {
		"newWithBackend:" : "HB 7/5/2019 15:29" },
	"instance" : {
		"addUser:" : "HB 7/5/2019 15:42",
		"backend" : "HB 7/5/2019 15:29",
		"backend:" : "HB 7/5/2019 15:29",
		"buildContactListWith:" : "HB 7/7/2019 22:30",
		"buildCreateChatButtonWith:" : "MD 7/4/2019 16:57",
		"buildWith:" : "MD 7/4/2019 16:56",
		"close" : "HB 7/5/2019 15:51",
		"contactNames" : "HB 7/5/2019 16:18",
		"createChat" : "HB 7/7/2019 22:31",
		"getContactIndex" : "HB 7/7/2019 22:31",
		"getSelectedUserId" : "HB 7/7/2019 22:30",
		"initialize" : "HB 7/7/2019 22:32",
		"receivedUsers:" : "HB 7/5/2019 15:44",
		"setContactIndex:" : "HB 7/7/2019 22:31",
		"userToUIString:" : "HB 7/5/2019 16:18" } }
