{
	"class" : {
		"newFor:" : "jkon 6/19/2024 18:26",
		"newFor:isExclusive:" : " 6/24/2024 10:41:19" },
	"instance" : {
		"addSelectionMorph" : "jkon 6/19/2024 18:32",
		"addTextMorph" : "jkon 6/17/2024 15:32",
		"content" : "jkon 6/17/2024 15:32",
		"content:" : "jkon 6/17/2024 15:32",
		"initialize" : "jkon 6/18/2024 10:03",
		"isExclusive" : " 6/24/2024 10:41:19",
		"isExclusive:" : " 6/24/2024 10:41:19",
		"isSelected" : "jkon 6/17/2024 14:52",
		"isSelected:" : "jkon 6/17/2024 14:52",
		"selectionMorph" : "jkon 6/17/2024 15:20",
		"selectionMorph:" : "jkon 6/17/2024 15:20",
		"updateChoice" : "jkon 6/18/2024 10:03" } }
